dox_style/__init__.py
dox_style/__main__.py
dox_style/version.py
dox_style/checks/__init__.py
dox_style/checks/check.py
dox_style/checks/dummy.py
dox_style/checks/finding.py
dox_style/checks/heading_levels_check.py
dox_style/checks/include_rst_check.py
dox_style/checks/main.py
dox_style/checks/top_level_casing_check.py
dox_style/checks/top_level_heading_check.py
dox_style/checks/top_level_length_check.py
dox_style/checks/top_level_modulename_check.py
dox_style/checks/trailing_whitespace_check.py
dox_style/checks/underline_length_check.py
dox_style/checks/utils.py
dox_style/config/label_check.py
dox_style/config/main.py
dox_style/config/_static/breadcrumbs.html
dox_style/config/_static/colored_table.css
dox_style/config/_static/colors.css
dox_style/config/_static/footer.html
dox_style/config/_static/header.css
dox_style/config/_static/rtd_theme_overrides.css
dox_style-0.2.1.dist-info/LICENSE
dox_style-0.2.1.dist-info/METADATA
dox_style-0.2.1.dist-info/WHEEL
dox_style-0.2.1.dist-info/top_level.txt
dox_style-0.2.1.dist-info/RECORD
