Metadata-Version: 2.1
Name: dox_style
Version: 0.2.1
Summary: Standard configuration, theme enhancements and style checks for Sphinx documentations.
Author: Accenture
License: Apache-2.0
Project-URL: Homepage, https://github.com/esrlabs/dox
Project-URL: Issues, https://github.com/esrlabs/dox/issues
Project-URL: Documentation, https://esrlabs.github.io/dox/dox_style
Classifier: Programming Language :: Python :: 3
Classifier: License :: OSI Approved :: Apache Software License
Classifier: Operating System :: OS Independent
Requires-Python: >=3.8
License-File: LICENSE
